[
  {
    "url": "https://www.alibaba.com/product-detail/SADOER-Private-Label-Organic-Lip-Balm_1601599815227.html?spm=a2700.prosearch.normal_offer.d_image.7c9a67afirCbCS\u0026selectedCarrierCode=SEMI_MANAGED_ECONOMIC%40%40ECONOMY\u0026priceId=37ae8e5e640a46e983cb6e0693895111",
    "categoria": "lip balms",
    "titulo": "SADOER Private Label Organic Lip Balm Stick Manufacturer's Moisturizing Nourish Repair Strawberry Peach Orange Avocado Lip Gloss",
    "imagenes": [
      "https://s.alicdn.com/@sc04/kf/H794c231ebf224b41b10c524392ea793fx.jpg_960x960q80.jpg",
      "https://s.alicdn.com/@sc04/kf/He1bbc1296aa9496ebd3dbda0f83f3aafC.jpg_960x960q80.jpg",
      "https://s.alicdn.com/@sc04/kf/H437a2092eb0c426986dc2ba05ae4e409j.jpg_960x960q80.jpg",
      "https://s.alicdn.com/@sc04/kf/Hc69bb0ea55044b53b45835c49bad64bc7.jpg_960x960q80.jpg",
      "https://s.alicdn.com/@sc04/kf/H33e34cd9f479462e98cc22bbbe303bb01.jpg_960x960q80.jpg",
      "https://s.alicdn.com/@sc04/kf/Hd9f54b74101d49dd9371690db4bfe79dw.jpg_960x960q80.jpg"
    ],
    "colores": [
      {
        "nombre": "Acura sandwich lip balm 2.5g",
        "imagen": "https://s.alicdn.com/@sc04/kf/H7c37271c1beb4c7cbbd26873bd4baeea0.jpg"
      },
      {
        "nombre": "Peach sandwich lip balm 2.5g",
        "imagen": "https://s.alicdn.com/@sc04/kf/H3839c117b6074ca5aceb5538a7144238N.jpg"
      },
      {
        "nombre": "Orange sandwich lip balm 2.5g",
        "imagen": "https://s.alicdn.com/@sc04/kf/Ha726dfaa5c284cf3865cabd57a4e904fm.jpg"
      }
    ],
    "tamaños": null,
    "precios": [
      {
        "cantidad": "2 - 9 pieces",
        "valor": "$0.72"
      },
      {
        "cantidad": "10 - 99 pieces",
        "valor": "$0.62"
      },
      {
        "cantidad": "100 - 999 pieces",
        "valor": "$0.52"
      },
      {
        "cantidad": "\u003e= 1000 pieces",
        "valor": "$0.42"
      }
    ],
    "bloque_logistico": "Standard: Shipping fee: FREE shipping | Guaranteed delivery: Nov 27 - Dec 07 || Economy: Shipping fee: FREE shipping | Guaranteed delivery: Nov 28 - Dec 08 || Premium: Shipping fee: $13.83 $33.83 for 2 pieces | Guaranteed delivery: Nov 24 - Dec 05",
    "detalles": {
      "Flavor": "Strawberry",
      "Selling Units": "Single item",
      "Single gross weight": "0.100 kg",
      "Single package size": "10X5X5 cm",
      "brand name": "SADOER",
      "feature": "waterproof",
      "form": "Stick",
      "gender": "Female",
      "ingredient": "Herbal",
      "model number": "NO.SD32131 37976 8634 8610",
      "net wt": "2.5g",
      "place of origin": "Guangdong, China",
      "size type": "regular size",
      "tube custom": "Accept"
    }
  },
  {
    "url": "https://www.alibaba.com/product-detail/OEM-ODM-Lip-Care-Set-Summer_1601563326215.html?spm=a2700.prosearch.normal_offer.d_image.7c9a67afirCbCS\u0026selectedCarrierCode=SEMI_MANAGED_ECONOMIC%40%40ECONOMY\u0026priceId=37ae8e5e640a46e983cb6e0693895111",
    "categoria": "lip balms",
    "titulo": "OEM\u0026ODM Lip Care Set Summer Moisturizing Hydrating Anti-Chapped Cream Colorful Fruit Extract Lip Balm",
    "imagenes": [
      "https://s.alicdn.com/@sc04/kf/H25cc8597e8fc438caebf63c4d283ad85U.png_960x960q80.jpg",
      "https://s.alicdn.com/@sc04/kf/H9341a1b149c54b7cbd800040f19ac9438.png_960x960q80.jpg",
      "https://s.alicdn.com/@sc04/kf/H25dfff2b0f874ecf92492114c40b9aa22.png_960x960q80.jpg",
      "https://s.alicdn.com/@sc04/kf/Hf0ffe6571f4b4db580906f804d317d67q.png_960x960q80.jpg",
      "https://s.alicdn.com/@sc04/kf/H89fed88c9ff74857ab22ff675d1462beA.png_960x960q80.jpg",
      "https://s.alicdn.com/@sc04/kf/H5e7e73369bb04952976b13ddf8b01bfbb.png_960x960q80.jpg"
    ],
    "colores": [
      {
        "nombre": "Pink",
        "imagen": "https://s.alicdn.com/@sc04/kf/Hff498a8ff51346caaf6153317a5fb1baW.png"
      }
    ],
    "tamaños": [
      "30 ml(1.01Fl Oz)",
      "Strawberry"
    ],
    "precios": [
      {
        "cantidad": "2 - 9 pieces",
        "valor": "$1.66"
      },
      {
        "cantidad": "10 - 99 pieces",
        "valor": "$1.60"
      },
      {
        "cantidad": "100 - 999 pieces",
        "valor": "$1.55"
      },
      {
        "cantidad": "\u003e= 1000 pieces",
        "valor": "$1.45"
      }
    ],
    "bloque_logistico": "Standard: Shipping fee: FREE shipping | Guaranteed delivery: Nov 27 - Dec 07 || Economy: Shipping fee: FREE shipping | Guaranteed delivery: Nov 28 - Dec 08 || Premium: Shipping fee: $13.83 $33.83 for 2 pieces | Guaranteed delivery: Nov 24 - Dec 05",
    "detalles": {
      "Selling Units": "Single item",
      "Single gross weight": "0.100 kg",
      "Single package size": "12X12X2 cm",
      "feature": "Moisturizer",
      "form": "MUD",
      "ingredient": "Organic",
      "main ingredient": "Jojoba Oil",
      "place of origin": "Guangdong, China",
      "skin type": "All Skin Types",
      "supply type": "OEM/ODM",
      "use": "Lips"
    }
  },
  {
    "url": "https://www.alibaba.com/product-detail/Gold-Foil-Color-Changing-Lipstick-Improve_1601460997481.html?spm=a2700.prosearch.normal_offer.d_image.7c9a67afirCbCS\u0026selectedCarrierCode=SEMI_MANAGED_ECONOMIC%40%40ECONOMY\u0026priceId=37ae8e5e640a46e983cb6e0693895111",
    "categoria": "lip balms",
    "titulo": "Gold Foil Color Changing Lipstick Improve Dull Dry Brighten Lips Long Lasting Nourishing Moisturizing Lip Balm",
    "imagenes": [
      "https://s.alicdn.com/@sc04/kf/H2d0f511769164167844d13d977ea55bcj.jpg_960x960q80.jpg",
      "https://s.alicdn.com/@sc04/kf/Hc757569e77ac498182564c064334e012L.jpg_960x960q80.jpg",
      "https://s.alicdn.com/@sc04/kf/H7015195765bf4ef6975b787e6a7e9a12b.jpg_960x960q80.jpg",
      "https://s.alicdn.com/@sc04/kf/H1c6c999c9ba1473fabfe2c2e45d3cf9aa.jpg_960x960q80.jpg",
      "https://s.alicdn.com/@sc04/kf/H1ddeefc0c9954c60b6d4674456060c308.jpg_960x960q80.jpg",
      "https://s.alicdn.com/@sc04/kf/H9bb690cddd4c43ae80ce8d2a2cdd24a2Y.jpg_960x960q80.jpg"
    ],
    "colores": [
      {
        "nombre": "Gold Foil",
        "imagen": "https://s.alicdn.com/@sc04/kf/H63eef8da6201451b98c06cc0bf3984228.jpg"
      },
      {
        "nombre": "Silver Foil",
        "imagen": "https://s.alicdn.com/@sc04/kf/Hbed8189b4e494831a17c8d4547530811k.jpg"
      },
      {
        "nombre": "Flower",
        "imagen": "https://s.alicdn.com/@sc04/kf/H91653e8466114fec9dfd8f53f45f88f4S.jpg"
      }
    ],
    "tamaños": null,
    "precios": [
      {
        "cantidad": "3 - 59 pieces",
        "valor": "$1.56"
      },
      {
        "cantidad": "60 - 499 pieces",
        "valor": "$1.34"
      },
      {
        "cantidad": "500 - 999 pieces",
        "valor": "$1.23"
      },
      {
        "cantidad": "\u003e= 1000 pieces",
        "valor": "$1.12"
      }
    ],
    "bloque_logistico": "Standard: Shipping fee: FREE shipping | Guaranteed delivery: Nov 24 - Dec 09 || Economy: Shipping fee: FREE shipping | Guaranteed delivery: Nov 25 - Dec 10 || Premium: Shipping fee: $13.83 $33.83 for 3 pieces | Guaranteed delivery: Nov 23 - Dec 05",
    "detalles": {
      "Selling Units": "Single item",
      "Single gross weight": "0.057 kg",
      "Single package size": "8.6X3.1X3.1 cm",
      "Style": "Modern, Cuté",
      "Type": "Sheer, Jelly",
      "brand name": "HelloKiss",
      "certification": "None",
      "feature": "Moisturizing",
      "form": "Stick",
      "ingredient": "Herbal, Mineral",
      "model number": "9909",
      "net wt": "2+1ml",
      "place of origin": "Guangdong, China",
      "size type": "regular size"
    }
  },
  {
    "url": "https://www.alibaba.com/product-detail/Own-Brand-Dilutes-Lip-Lines-Moisturizes_1601564839973.html?spm=a2700.prosearch.normal_offer.d_image.7c9a67afirCbCS\u0026selectedCarrierCode=SEMI_MANAGED_ECONOMIC%40%40ECONOMY\u0026priceId=37ae8e5e640a46e983cb6e0693895111",
    "categoria": "lip balms",
    "titulo": "Own Brand Dilutes Lip Lines Moisturizes and Hydrates Cheese Children'S Lasting Moisturizing and Temperature-Changing Lip Balm",
    "imagenes": [
      "https://s.alicdn.com/@sc04/kf/H9687fa7ad22a4fc8ada4b67a390192bdL.jpg_960x960q80.jpg",
      "https://s.alicdn.com/@sc04/kf/He3af73c8f23246a99db8eebc1946c8b3Q.png_960x960q80.jpg",
      "https://s.alicdn.com/@sc04/kf/Hd32e26ea6f08435d9ca1dc7157463a6dg.png_960x960q80.jpg",
      "https://s.alicdn.com/@sc04/kf/H91bd2c06fde748bc8c91dd11f79fa0e1m.png_960x960q80.jpg",
      "https://s.alicdn.com/@sc04/kf/H7c19d38ccde242029f2577079ff3b75fV.png_960x960q80.jpg",
      "https://s.alicdn.com/@sc04/kf/H18d97558d99f4471928d875a3f0e50a4n.jpg_960x960q80.jpg"
    ],
    "colores": [
      {
        "nombre": "01 cheese yellow",
        "imagen": "https://s.alicdn.com/@sc04/kf/Hce5f2fabab254f0399d7b75745ec4989J.png"
      },
      {
        "nombre": "02 lithospermum",
        "imagen": "https://s.alicdn.com/@sc04/kf/H5e3cffcca7c64653ac647fc0f92bcea0U.png"
      },
      {
        "nombre": "03 black beans",
        "imagen": "https://s.alicdn.com/@sc04/kf/Hb6ab1cdd452f4a6ca9503449f258066ff.png"
      }
    ],
    "tamaños": null,
    "precios": [
      {
        "cantidad": "3 - 9 pieces",
        "valor": "$1.11"
      },
      {
        "cantidad": "10 - 99 pieces",
        "valor": "$1.10"
      },
      {
        "cantidad": "100 - 999 pieces",
        "valor": "$0.90"
      },
      {
        "cantidad": "\u003e= 1000 pieces",
        "valor": "$0.70"
      }
    ],
    "bloque_logistico": "Standard: Shipping fee: FREE shipping | Guaranteed delivery: Nov 27 - Dec 07 || Economy: Shipping fee: FREE shipping | Guaranteed delivery: Nov 28 - Dec 08 || Premium: Shipping fee: $17.76 $37.76 for 3 pieces | Guaranteed delivery: Nov 24 - Dec 05",
    "detalles": {
      "Selling Units": "Single item",
      "Single gross weight": "0.050 kg",
      "Single package size": "20X20X3 cm",
      "Style": "Fashionable",
      "Type": "Lip balm",
      "brand name": "OEM\u0026ODM\u0026OBM",
      "certification": "MSDS",
      "feature": "waterproof",
      "form": "Cream",
      "ingredient": "Mineral",
      "model number": "MAGIC CASA",
      "net wt": "8g",
      "place of origin": "Guangdong, China",
      "size type": "regular size"
    }
  },
  {
    "url": "https://www.alibaba.com/product-detail/Wholesale-Lip-Balm-Private-Label-New_1601377530904.html?spm=a2700.prosearch.normal_offer.d_image.7c9a67afirCbCS\u0026selectedCarrierCode=SEMI_MANAGED_ECONOMIC%40%40ECONOMY\u0026priceId=37ae8e5e640a46e983cb6e0693895111",
    "categoria": "lip balms",
    "titulo": "Wholesale Lip Balm Private Label New Lip protection Set Colorless Moisturizing Plant Extract",
    "imagenes": [
      "https://s.alicdn.com/@sc04/kf/Hba8447e2b85b46c2bb561dc56c82b24bY.jpg_960x960q80.jpg",
      "https://s.alicdn.com/@sc04/kf/H8ccdd6eb696d426a8067061772a39944e.jpg_960x960q80.jpg",
      "https://s.alicdn.com/@sc04/kf/Hcfb657f4e794434e879f892223a51e6eF.jpg_960x960q80.jpg",
      "https://s.alicdn.com/@sc04/kf/Hefdd7ba111a9457283489448f031b080Y.jpg_960x960q80.jpg",
      "https://s.alicdn.com/@sc04/kf/Hbfef90fd426543e4ba16ade9531942fe7.jpg_960x960q80.jpg",
      "https://s.alicdn.com/@sc04/kf/H698cd8ad47e64d88ad351d44755ef2d9s.jpg_960x960q80.jpg"
    ],
    "colores": null,
    "tamaños": [
      "01#"
    ],
    "precios": [
      {
        "cantidad": "2 - 499 pieces",
        "valor": "$0.96"
      },
      {
        "cantidad": "500 - 999 pieces",
        "valor": "$0.83"
      },
      {
        "cantidad": "\u003e= 1000 pieces",
        "valor": "$0.77"
      }
    ],
    "bloque_logistico": "Standard: Shipping fee: FREE shipping | Guaranteed delivery: Nov 27 - Dec 07 || Economy: Shipping fee: FREE shipping | Guaranteed delivery: Nov 28 - Dec 08 || Premium: Shipping fee: $13.83 $33.83 for 2 pieces | Guaranteed delivery: Nov 24 - Dec 05",
    "detalles": {
      "Flavor": "Fruit",
      "Logo/graphic design": "Laser Printing, Heat-Transfer Printing, silicone printing, Digital Printing, Transfer Sticker, Labeling, Silk Screen Printing",
      "Selling Units": "Single item",
      "Single gross weight": "0.090 kg",
      "Single package size": "13X12X5 cm",
      "Type": "Beauty Lip Makeup Cosmetics, Lip Balm",
      "Use": "Lips",
      "brand name": "Gege Bear",
      "feature": "waterproof",
      "form": "Stick",
      "gender": "Female",
      "ingredient": "Herbal",
      "model number": "SL282-3",
      "net wt": "3g+3.8g",
      "place of origin": "Guangdong, China",
      "size type": "regular size"
    }
  },
  {
    "url": "https://www.alibaba.com/product-detail/Lip-Lacquer-Moisturizing-Shiny-Non-Sticky_1600896990119.html?spm=a2700.details.you_may_like.5.2ad44b64QTiMwJ",
    "categoria": "lip balms",
    "titulo": "Lip Lacquer Moisturizing Shiny Non-Sticky Long Lasting Provides 6 Colors Lipstick Oil Lip Care",
    "imagenes": [
      "https://s.alicdn.com/@sc04/kf/He927ee7ba3e74709a3531ba0ff788533o.png_960x960q80.jpg",
      "https://s.alicdn.com/@sc04/kf/H93d9e447a5e14433b1b20e1206cee672y.jpg_960x960q80.jpg",
      "https://s.alicdn.com/@sc04/kf/H431ead5cb3224d4eac331e6398f467d15.jpg_960x960q80.jpg",
      "https://s.alicdn.com/@sc04/kf/H9764dc331d4d4c84a60d8ca2ff2a781dS.jpg_960x960q80.jpg",
      "https://s.alicdn.com/@sc04/kf/H68cecffa2ddb459f9eb7cf604d74bb3d3.png_960x960q80.jpg",
      "https://s.alicdn.com/@sc04/kf/H5bd6bff232dd4064a428c9119efb490b2.png_960x960q80.jpg"
    ],
    "colores": [
      {
        "nombre": "02#orange",
        "imagen": "https://s.alicdn.com/@sc04/kf/H0ae50ec896674edebb6f81910d48448du.jpg"
      },
      {
        "nombre": "01#light pink",
        "imagen": "https://s.alicdn.com/@sc04/kf/H35deb6329aa34948b4b3d870caf08936z.png"
      },
      {
        "nombre": "03#light purple",
        "imagen": "https://s.alicdn.com/@sc04/kf/H93dffdf3010b41a2a44e4be2e7f4e3e2J.jpg"
      },
      {
        "nombre": "04#wine red",
        "imagen": "https://s.alicdn.com/@sc04/kf/Hf6a9a947c77a44169d031a74761ddac4z.png"
      },
      {
        "nombre": "05#purple",
        "imagen": "https://s.alicdn.com/@sc04/kf/Hbfccb9a3c2ef480a85d7467576aa6b46Z.jpg"
      },
      {
        "nombre": "06#white",
        "imagen": "https://s.alicdn.com/@sc04/kf/He37ccecd1d3a43b49a19a7565f4ae1ffH.png"
      }
    ],
    "tamaños": null,
    "precios": [
      {
        "cantidad": "3 - 59 pieces",
        "valor": "$1.15"
      },
      {
        "cantidad": "60 - 499 pieces",
        "valor": "$0.99"
      },
      {
        "cantidad": "500 - 999 pieces",
        "valor": "$0.91"
      },
      {
        "cantidad": "\u003e= 1000 pieces",
        "valor": "$0.85"
      }
    ],
    "bloque_logistico": "Economy: Shipping fee: FREE shipping | Guaranteed delivery: Nov 21 - Dec 01 || Standard: Shipping fee: FREE shipping | Guaranteed delivery: Nov 21 - Nov 30 || Premium: Shipping fee: $13.83 $33.83 for 3 pieces | Guaranteed delivery: Nov 17 - Nov 25",
    "detalles": {
      "Certification": "MSDS",
      "Color": "White",
      "Function": "Hydrating Lip Moisturizing",
      "Keywords": "Lip Lacquer Moisturizing",
      "Low MOQ": "3 pcs",
      "Product name": "Hydrating Lip Glow Oil",
      "Sample": "Paid Samples Avaliable",
      "Selling Units": "Single item",
      "Service": "Print LOGO.Samples Order.OEM.ODM",
      "Shelf Life": "3 Years",
      "Single gross weight": "0.045 kg",
      "Single package size": "8.1X3.1X3.1 cm",
      "Skin Type": "All skin Types",
      "brand name": "HelloKiss",
      "certification": "MSDS",
      "feature": "Sunscreen, waterproof, Long-lasting, Moisturizing",
      "form": "Liquid",
      "ingredient": "Chemical, Vegan",
      "model number": "9901",
      "net wt": "8ml(0.27Fl Oz)",
      "place of origin": "Guangdong, China",
      "size type": "regular size"
    }
  },
  {
    "url": "https://www.alibaba.com/product-detail/BLIW-Private-Label-Organic-Rose-Moisturising_1601395043987.html?spm=a2700.prosearch.normal_offer.d_image.383967af6NcHMt\u0026selectedCarrierCode=SEMI_MANAGED_ECONOMIC%40%40ECONOMY\u0026priceId=1f34c49186b54c839e0d1cfb30c7b030",
    "categoria": "skincare",
    "titulo": "BLIW Private Label Organic Rose Moisturising Anti-Wrinkle Hydrating Cream with Sweet and Fresh Smelling Skin Care Essential Oils",
    "imagenes": [
      "https://s.alicdn.com/@sc04/kf/H69cb7ee962994874a246131c2a694566t.png_960x960q80.jpg",
      "https://s.alicdn.com/@sc04/kf/H1f7626ed12d54ea3a6754b0b0cddf8dad.png_960x960q80.jpg",
      "https://s.alicdn.com/@sc04/kf/Hf753376516b74e7999e341dfcfa195ef2.png_960x960q80.jpg",
      "https://s.alicdn.com/@sc04/kf/H3dabcf75abe54a9fb7918e16d93a54326.png_960x960q80.jpg",
      "https://s.alicdn.com/@sc04/kf/Hdfdfcdafb5b94316a9ce32e0fc9f2ae8C.png_960x960q80.jpg"
    ],
    "colores": [
      {
        "nombre": "Phoenix Face Oil",
        "imagen": "https://s.alicdn.com/@sc04/kf/H65262ad22c21477eabec0afc0b296c8av.jpg"
      }
    ],
    "tamaños": [
      "30 ml"
    ],
    "precios": [
      {
        "cantidad": "3 - 299 pieces",
        "valor": "$2.65"
      },
      {
        "cantidad": "300 - 4999 pieces",
        "valor": "$2.20"
      },
      {
        "cantidad": "\u003e= 5000 pieces",
        "valor": "$1.25"
      }
    ],
    "bloque_logistico": "Standard: Shipping fee: FREE shipping | Guaranteed delivery: Nov 24 - Dec 09 || Economy: Shipping fee: FREE shipping | Guaranteed delivery: Nov 25 - Dec 10 || Premium: Shipping fee: $13.83 $33.83 for 3 pieces | Guaranteed delivery: Nov 23 - Dec 05",
    "detalles": {
      "Available Quantity": "10000",
      "Function": "Health Care Skincare Beauty",
      "Keywords": "Massage oil",
      "MOQ": "100pcs",
      "Product name": "Phoenix facial oil",
      "Selling Units": "Single item",
      "Shelf life": "3 Years",
      "Single gross weight": "0.200 kg",
      "Single package size": "6X6X6 cm",
      "Skin Type": "All Skin Types",
      "Supply Type": "OEM ODM",
      "Volume": "30 Ml",
      "brand name": "OEM",
      "feature": "Skin Revitalizer, Anti-Puffiness, Moisturizer, Anti-Wrinkle, Firming",
      "ingredient": "Phoenix",
      "model number": "Phoenix facial oil",
      "odor": "Sweet, Floral, Fresh",
      "place of origin": "Guangdong, China",
      "raw material": "Flowers",
      "type": "Compound Essential Oil"
    }
  },
  {
    "url": "https://www.alibaba.com/product-detail/12-Colors-Highlighter-Blush-Contour-Stick_1601445465865.html?spm=a2700.prosearch.normal_offer.d_image.383967af6NcHMt\u0026selectedCarrierCode=SEMI_MANAGED_ECONOMIC%40%40ECONOMY\u0026priceId=1f34c49186b54c839e0d1cfb30c7b030",
    "categoria": "skincare",
    "titulo": "12 Colors Highlighter Blush Contour Stick Shimmer Long-lasting Cosmetics Stick Face Makeup Bronzer Stick",
    "imagenes": [
      "https://s.alicdn.com/@sc04/kf/H3c00f586575e4f6c955112f16407e147u.png_960x960q80.jpg",
      "https://s.alicdn.com/@sc04/kf/H0c57e2154c2f4c8ea58bf37909a996cfx.png_960x960q80.jpg",
      "https://s.alicdn.com/@sc04/kf/He43409c529c14db1b9c900bf9ff365b3h.png_960x960q80.jpg",
      "https://s.alicdn.com/@sc04/kf/H155ab76741134d318314288354eac36fk.png_960x960q80.jpg",
      "https://s.alicdn.com/@sc04/kf/H31f0dfe2dabf4936a1749b374edacc1de.png_960x960q80.jpg",
      "https://s.alicdn.com/@sc04/kf/Hfd2c05f19b7a465f97087dec395f73b0v.png_960x960q80.jpg"
    ],
    "colores": [
      {
        "nombre": "01#highlighter",
        "imagen": "https://s.alicdn.com/@sc04/kf/H1815b56f7ca340b78116cc95b3cad2d3U.png"
      },
      {
        "nombre": "02#highlighter",
        "imagen": "https://s.alicdn.com/@sc04/kf/H1594600b1dac4a68a87c253204a86583Q.png"
      },
      {
        "nombre": "03#highlighter",
        "imagen": "https://s.alicdn.com/@sc04/kf/H4c400505ba304d0093840a4e3b9c17bdf.png"
      },
      {
        "nombre": "04#highlighter",
        "imagen": "https://s.alicdn.com/@sc04/kf/H00310acd6f554bc7a541901356cd2473A.png"
      },
      {
        "nombre": "05#highlighter",
        "imagen": "https://s.alicdn.com/@sc04/kf/H87db88d2da5840f691f684b2ba5190d1m.png"
      },
      {
        "nombre": "06#contour",
        "imagen": "https://s.alicdn.com/@sc04/kf/H0b91dde5625a41be9bf875bf281177b3j.png"
      }
    ],
    "tamaños": null,
    "precios": [
      {
        "cantidad": "3 - 59 pieces",
        "valor": "$1.24"
      },
      {
        "cantidad": "60 - 499 pieces",
        "valor": "$1.06"
      },
      {
        "cantidad": "500 - 999 pieces",
        "valor": "$0.97"
      },
      {
        "cantidad": "\u003e= 1000 pieces",
        "valor": "$0.88"
      }
    ],
    "bloque_logistico": "Standard: Shipping fee: FREE shipping | Guaranteed delivery: Nov 24 - Dec 09 || Economy: Shipping fee: FREE shipping | Guaranteed delivery: Nov 25 - Dec 10 || Premium: Shipping fee: $13.83 $33.83 for 3 pieces | Guaranteed delivery: Nov 23 - Dec 05",
    "detalles": {
      "Selling Units": "Single item",
      "Single gross weight": "0.038 kg",
      "Single package size": "7X3.5X3.5 cm",
      "brand name": "HelloKiss",
      "feature": "Sunscreen, waterproof, Contouring",
      "form": "Stick",
      "ingredient": "Mineral",
      "model number": "9517",
      "place of origin": "Guangdong, China"
    }
  },
  {
    "url": "https://www.alibaba.com/product-detail/OEM-2oz-4oz-Beef-Tallow-Skincare_1601434995603.html?spm=a2700.prosearch.normal_offer.d_image.383967af6NcHMt\u0026selectedCarrierCode=SEMI_MANAGED_ECONOMIC%40%40ECONOMY\u0026priceId=1f34c49186b54c839e0d1cfb30c7b030",
    "categoria": "skincare",
    "titulo": "OEM 2oz 4oz Beef Tallow Skincare Honey Balm Organic Halal Certified Vanilla Whipped Tallow Moisturizer | 100% Natural Skincare",
    "imagenes": [
      "https://s.alicdn.com/@sc04/kf/H0ed12c514ed847a782067ee8c7f2202fu.jpg_960x960q80.jpg",
      "https://s.alicdn.com/@sc04/kf/H3b604be16ed44111b7bfc39830d8a658c.jpg_960x960q80.jpg",
      "https://s.alicdn.com/@sc04/kf/H8d0855bd36b249499811b7af62eb2604S.jpg_960x960q80.jpg",
      "https://s.alicdn.com/@sc04/kf/Hc588797fdf754699a0f35f4ad63f13a8O.jpg_960x960q80.jpg",
      "https://s.alicdn.com/@sc04/kf/H8939755123684146811eda87a1a410fbl.jpg_960x960q80.jpg",
      "https://s.alicdn.com/@sc04/kf/Hf3dfaa0c43934498b3773a021e010083n.jpg_960x960q80.jpg"
    ],
    "colores": [
      {
        "nombre": "113g WHIPPED TALLOW HONEY BALM (UNSCENTED)",
        "imagen": "https://s.alicdn.com/@sc04/kf/Hce76087bac0444d6a2d4a99416abdcfa9.png"
      },
      {
        "nombre": "113g WHIPPED TALLOW HONEY BALM (LAVENDER)",
        "imagen": "https://s.alicdn.com/@sc04/kf/H61de8ea9e49e46dc862ce73dc3e4d69c2.png"
      },
      {
        "nombre": "113g WHIPPED TALLOW HONEY BALM (CITRUS)",
        "imagen": "https://s.alicdn.com/@sc04/kf/Hff071d10e5564866b8aee5fa98baf723e.png"
      }
    ],
    "tamaños": [
      "113g"
    ],
    "precios": [
      {
        "cantidad": "2 - 59 pieces",
        "valor": "$3.56"
      },
      {
        "cantidad": "60 - 999 pieces",
        "valor": "$2.35"
      },
      {
        "cantidad": "1000 - 19999 pieces",
        "valor": "$2.15"
      },
      {
        "cantidad": "\u003e= 20000 pieces",
        "valor": "$1.40"
      }
    ],
    "bloque_logistico": "Standard: Shipping fee: FREE shipping | Guaranteed delivery: Nov 24 - Dec 09 || Economy: Shipping fee: FREE shipping | Guaranteed delivery: Nov 25 - Dec 10 || Premium: Shipping fee: $17.44 $37.44 for 2 pieces | Guaranteed delivery: Nov 23 - Dec 05",
    "detalles": {
      "Brand": "MELAO",
      "Delivery Time": "7-30Days",
      "Form": "BALM",
      "Function": "Moisturizing,Fade Fine Lines,Repair The Barrier",
      "Ingredient": "60g/2 oz",
      "MOQ": "1000pcs",
      "Package": "Paper Box",
      "Packing": "Bottle",
      "Product name": "TALLOW skin care",
      "Selling Units": "Single item",
      "Service": "OEM ODM Private Label Service",
      "Shelf Life": "3 Years",
      "Single gross weight": "0.270 kg",
      "Single package size": "8X8X8 cm",
      "Type": "Private Label",
      "Use": "Face",
      "age group": "Adults",
      "application": "For Home Use",
      "brand name": "MELAO",
      "feature": "Whitening, Skin Revitalizer, Nourishing, Firming, Moisturizer, Anti-Allergy",
      "gender": "Female",
      "ingredient": "Glycerin, ADEPS BOVIS, BUTYLENE GLYCOL,",
      "main ingredient": "Glycerin, Vitamin E, ADEPS BOVIS, Butylene glycol, 100% GRASS FED TALLOW, HONEY, OLEA EUROPAEA (OLIVE) FRUIT OIL",
      "model number": "MELAO.YCR1003",
      "place of origin": "Guangdong, China",
      "skin type": "All Skin Types",
      "time used": "Night"
    }
  },
  {
    "url": "https://www.alibaba.com/product-detail/Retinol-Booster-Serum-Skin-Care-for_1601565603187.html?spm=a2700.prosearch.normal_offer.d_image.383967af6NcHMt\u0026selectedCarrierCode=SEMI_MANAGED_ECONOMIC%40%40ECONOMY\u0026priceId=1f34c49186b54c839e0d1cfb30c7b030",
    "categoria": "skincare",
    "titulo": "Retinol Booster Serum Skin Care for Face \u0026 Body, Retinol Face Cream Targets Uneven Tone, Fine Lines \u0026Sensitive Skin Repair",
    "imagenes": [
      "https://s.alicdn.com/@sc04/kf/Hd832321581ec4190b40c33a204a1b577C.jpg_960x960q80.jpg",
      "https://s.alicdn.com/@sc04/kf/H15d35d950b194fe1804a3d2037eb9416L.jpg_960x960q80.jpg",
      "https://s.alicdn.com/@sc04/kf/Hd2334f4a624140d59a76ea305b2d0c02i.jpg_960x960q80.jpg",
      "https://s.alicdn.com/@sc04/kf/H0c215035fd4f4295aaa192163f0d1d11g.jpg_960x960q80.jpg",
      "https://s.alicdn.com/@sc04/kf/H300d1aad28c944a48d7f8e727769e3ce8.jpg_960x960q80.jpg",
      "https://s.alicdn.com/@sc04/kf/H271978a6c54f41b78e602d1c71a2c5b8B.jpg_960x960q80.jpg"
    ],
    "colores": [
      {
        "nombre": "Retinol Cream",
        "imagen": "https://s.alicdn.com/@sc04/kf/Hffea38da2ab04f2d8ae401458084afa0i.jpg"
      }
    ],
    "tamaños": [
      "30ml(1.01Fl Oz)"
    ],
    "precios": [
      {
        "cantidad": "2 - 499 pieces",
        "valor": "$1.12"
      },
      {
        "cantidad": "500 - 999 pieces",
        "valor": "$0.98"
      },
      {
        "cantidad": "\u003e= 1000 pieces",
        "valor": "$0.84"
      }
    ],
    "bloque_logistico": "Standard: Shipping fee: FREE shipping | Guaranteed delivery: Nov 24 - Dec 09 || Economy: Shipping fee: FREE shipping | Guaranteed delivery: Nov 25 - Dec 10 || Premium: Shipping fee: $13.83 $33.83 for 2 pieces | Guaranteed delivery: Nov 23 - Dec 05",
    "detalles": {
      "Advantage": "Professional Face Cream",
      "Certification": "MSDS",
      "Effect": "Anti Wrinkle  Rejuvenating Moisturizing",
      "Form": "Cream",
      "Function": "Moisturizng",
      "Keywords": "Skincare Cream",
      "Packing": "Box",
      "Product name": "Retinol Cream",
      "Selling Units": "Single item",
      "Single gross weight": "0.120 kg",
      "Single package size": "5.5X5.5X4.2 cm",
      "Type": "Skin Care Beauty Product",
      "Usage": "Skin Care Treatments",
      "Use": "Face Skincare",
      "Volume": "30ml",
      "age group": "Adults",
      "application": "For Home Use",
      "brand name": "YURHERSU",
      "feature": "Anti-Aging, Moisturizer",
      "gender": "Female",
      "ingredient": "Hyaluronic acid, Fragrance-free, Paraben-Free",
      "main ingredient": "Hyaluronic acid, Retinol",
      "model number": "PC394",
      "place of origin": "Guangdong, China",
      "skin type": "All Skin Types",
      "time used": "Night"
    }
  },
  {
    "url": "https://www.alibaba.com/product-detail/Facial-Cleanser-Vitamins-Anti-Aging-Korean_1601178665462.html?spm=a2700.details.you_may_like.1.74d81bcbsCxoJS",
    "categoria": "skincare",
    "titulo": "Facial Cleanser Vitamins Anti Aging Korean Skin Care Cosmetic Beauty Face Skin Care Whitening Skin Care Products Turmeric Soap",
    "imagenes": [
      "https://s.alicdn.com/@sc04/kf/H0b43144be8944ceda802c1bb3fe3e67fq.jpg_960x960q80.jpg",
      "https://s.alicdn.com/@sc04/kf/Hdc3b73ec765f429db5a7d5340de517e9G.jpg_960x960q80.jpg",
      "https://s.alicdn.com/@sc04/kf/H1fac1974965a404487b8bca04d3c3df4e.jpg_960x960q80.jpg",
      "https://s.alicdn.com/@sc04/kf/Hc72e004131144b85ba49054ec2da8bfd0.jpg_960x960q80.jpg",
      "https://s.alicdn.com/@sc04/kf/H837485c4587447b79b1f644c5e8aa443w.jpg_960x960q80.jpg",
      "https://s.alicdn.com/@sc04/kf/Hf192967fdb3145e8981d2fa5cc81966e7.png_960x960q80.jpg"
    ],
    "colores": null,
    "tamaños": [
      "turmeric soap"
    ],
    "precios": [
      {
        "cantidad": "2 - 99 pieces",
        "valor": "$1.22"
      },
      {
        "cantidad": "100 - 999 pieces",
        "valor": "$0.61"
      },
      {
        "cantidad": "1000 - 19999 pieces",
        "valor": "$0.55"
      },
      {
        "cantidad": "\u003e= 20000 pieces",
        "valor": "$0.29"
      }
    ],
    "bloque_logistico": "Standard: Shipping fee: FREE shipping | Guaranteed delivery: Nov 24 - Dec 09 || Economy: Shipping fee: FREE shipping | Guaranteed delivery: Nov 25 - Dec 10 || Premium: Shipping fee: $13.51 $33.51 for 2 pieces | Guaranteed delivery: Nov 23 - Dec 05",
    "detalles": {
      "Advantage": "Natural Organic",
      "Brand": "MELAO",
      "Function": "Whitening Effect",
      "Product Keywords": "Natural Handmade Organic Soap",
      "Product Name": "turmeric soap",
      "Sample": "Avialable",
      "Selling Units": "Single item",
      "Service": "OEM  ODM  Private Label",
      "Shelf Life": "3 Yeras",
      "Single gross weight": "0.110 kg",
      "Single package size": "6X3X6 cm",
      "Skin type": "All-skin",
      "Usage": "Daily Skin Care",
      "Volume": "100g*2",
      "age group": "Adults",
      "feature": "Basic Cleaning, Whitening, ANTI ACNE",
      "form": "Solid",
      "handmade": "Yes",
      "ingredient": "Herbal",
      "medicated": "No",
      "model number": "MELAO-W422",
      "place of origin": "Guangdong, China",
      "size type": "regular size",
      "transparent": "No",
      "type": "Toilet Soap"
    }
  },
  {
    "url": "https://www.alibaba.com/product-detail/Facial-Cleanser-Vitamins-Moisturizing-Anti-Aging_1601204654815.html?spm=a2700.details.you_may_like.2.74d81bcbsCxoJS",
    "categoria": "skincare",
    "titulo": "Facial Cleanser Vitamins Moisturizing Anti Aging Korean Cosmetic Beauty Face Whitening Skin Care Products Beef Tallow Soap",
    "imagenes": [
      "https://s.alicdn.com/@sc04/kf/H236f00c198b64bb9b807f0c9b1cf4d5eP.jpg_960x960q80.jpg",
      "https://s.alicdn.com/@sc04/kf/Hd597e6dbeebc466f84f6b6710a524c50F.jpg_960x960q80.jpg",
      "https://s.alicdn.com/@sc04/kf/H595cbe2b3fdf4db2b7f8eda3be1d97a2Z.jpg_960x960q80.jpg",
      "https://s.alicdn.com/@sc04/kf/Hfdd11ed0790d4cdeb518c2bea23daea0w.jpg_960x960q80.jpg",
      "https://s.alicdn.com/@sc04/kf/Hc6b292bd62f5449a826ea2f71d97bd468.jpg_960x960q80.jpg",
      "https://s.alicdn.com/@sc04/kf/H065cfb449d56445dadb206aa3b3d4fa3y.jpg_960x960q80.jpg"
    ],
    "colores": null,
    "tamaños": [
      "beef tallow soap"
    ],
    "precios": [
      {
        "cantidad": "2 - 119 pieces",
        "valor": "$2.65"
      },
      {
        "cantidad": "120 - 999 pieces",
        "valor": "$1.33"
      },
      {
        "cantidad": "1000 - 19999 pieces",
        "valor": "$1.20"
      },
      {
        "cantidad": "\u003e= 20000 pieces",
        "valor": "$0.36"
      }
    ],
    "bloque_logistico": "Standard: Shipping fee: FREE shipping | Guaranteed delivery: Nov 24 - Dec 09 || Economy: Shipping fee: FREE shipping | Guaranteed delivery: Nov 25 - Dec 10 || Premium: Shipping fee: $13.51 $33.51 for 2 pieces | Guaranteed delivery: Nov 23 - Dec 05",
    "detalles": {
      "Advantage": "Natural Organic",
      "Brand": "MELAO",
      "Function": "Whitening Effect",
      "Product Keywords": "Natural Handmade Organic Soap",
      "Product Name": "turmeric soap",
      "Sample": "Avialable",
      "Selling Units": "Single item",
      "Service": "OEM  ODM  Private Label",
      "Shelf Life": "3 Yeras",
      "Single gross weight": "0.150 kg",
      "Single package size": "7.5X3X6 cm",
      "Skin type": "All-skin",
      "Usage": "Daily Skin Care",
      "Volume": "100g*2",
      "age group": "Adults",
      "feature": "Basic Cleaning, Whitening, ANTI ACNE",
      "form": "Solid",
      "handmade": "Yes",
      "ingredient": "Herbal",
      "medicated": "No",
      "model number": "MELAO-W422",
      "place of origin": "Guangdong, China",
      "size type": "regular size",
      "transparent": "No",
      "type": "Toilet Soap"
    }
  },
  {
    "url": "https://www.alibaba.com/product-detail/Facial-Cleanser-Vitamins-Anti-Aging-Korean_1601166509628.html?spm=a2700.details.you_may_like.3.74d81bcbsCxoJS",
    "categoria": "skincare",
    "titulo": "Facial Cleanser Vitamins Anti Aging Korean Skin Care Cosmetic Beauty Face Skin Care Whitening Skin Care Products Kojic Acid Soap",
    "imagenes": [
      "https://s.alicdn.com/@sc04/kf/Hc3033eff33b6482ab862e940d97606130.jpg_960x960q80.jpg",
      "https://s.alicdn.com/@sc04/kf/Hca91f58d91604564adb41f238a1f23b7d.jpg_960x960q80.jpg",
      "https://s.alicdn.com/@sc04/kf/H89b51331bb144d07bfc4f6dbbc2f6b10v.jpg_960x960q80.jpg",
      "https://s.alicdn.com/@sc04/kf/H3dcad973fd9d4bc59f6232ac6695e6dcN.jpg_960x960q80.jpg",
      "https://s.alicdn.com/@sc04/kf/Ha2e04a578cea4854ae87fe42c801d707i.jpg_960x960q80.jpg",
      "https://s.alicdn.com/@sc04/kf/Haa0de54ac6324b8294b165adafc5ef56l.jpg_960x960q80.jpg"
    ],
    "colores": null,
    "tamaños": [
      "Kojic"
    ],
    "precios": [
      {
        "cantidad": "2 - 49 pieces",
        "valor": "$2"
      },
      {
        "cantidad": "50 - 999 pieces",
        "valor": "$0.96"
      },
      {
        "cantidad": "1000 - 19999 pieces",
        "valor": "$0.77"
      },
      {
        "cantidad": "\u003e= 20000 pieces",
        "valor": "$0.64"
      }
    ],
    "bloque_logistico": "Standard: Shipping fee: FREE shipping | Guaranteed delivery: Nov 24 - Dec 09 || Economy: Shipping fee: FREE shipping | Guaranteed delivery: Nov 25 - Dec 10 || Premium: Shipping fee: $17.44 $37.44 for 2 pieces | Guaranteed delivery: Nov 23 - Dec 05",
    "detalles": {
      "Advantage": "Natural Organic",
      "Brand": "MELAO",
      "Function": "Whitening Effect",
      "Product Keywords": "Natural Handmade Organic Soap",
      "Product Name": "Kojic acid soap",
      "Sample": "Avialable",
      "Selling Units": "Single item",
      "Service": "OEM  ODM  Private Label",
      "Shelf Life": "3 Yeras",
      "Single gross weight": "0.251 kg",
      "Single package size": "5.5X8.3X6 cm",
      "Skin Type": "All skin types",
      "Skin type": "All-skin",
      "Usage": "Daily Skin Care",
      "Volume": "100g*2",
      "age group": "Adults",
      "feature": "Basic Cleaning, Whitening, ANTI ACNE",
      "form": "Solid",
      "handmade": "Yes",
      "ingredient": "Herbal",
      "medicated": "No",
      "model number": "MELAO.KJYCR725",
      "place of origin": "Guangdong, China",
      "size type": "regular size",
      "transparent": "No",
      "type": "Toilet Soap"
    }
  },
  {
    "url": "https://www.alibaba.com/product-detail/YANJIE-Natural-Full-Strip-Magnetic-False_1601518267035.html?spm=a2700.prosearch.normal_offer.d_image.23f067afBH7NrD\u0026selectedCarrierCode=SEMI_MANAGED_STANDARD%40%40STANDARD\u0026priceId=fbece069f0f5430aa84b29fd92f587bc",
    "categoria": "makeup",
    "titulo": "YANJIE Natural Full Strip Magnetic False Eyelashes Kit C/D Curl Reusable Extensions 10 Magnets Soft Magnet Band Light Weight",
    "imagenes": [
      "https://s.alicdn.com/@sc04/kf/H095ac5110d604653a79a28bea955aef1I.jpg_960x960q80.jpg",
      "https://s.alicdn.com/@sc04/kf/Hb3a7218648a64fab87397c4e9534936fk.jpg_960x960q80.jpg",
      "https://s.alicdn.com/@sc04/kf/H58d1998290ef45a39c61199fe10e6961A.jpg_960x960q80.jpg",
      "https://s.alicdn.com/@sc04/kf/H6f7b1abdade5497ca6ff4015119695adM.jpg_960x960q80.jpg",
      "https://s.alicdn.com/@sc04/kf/H4bdefa36fc994619b18edeeb220b95f8K.jpg_960x960q80.jpg",
      "https://s.alicdn.com/@sc04/kf/H0232cacab4e64e79b188bb5aff9b96a8n.jpg_960x960q80.jpg"
    ],
    "colores": [
      {
        "nombre": "01 Delicate eyelashes",
        "imagen": "https://s.alicdn.com/@sc04/kf/H96f315c783124e8484e5bb4d74bae6741.jpg"
      },
      {
        "nombre": "02 Lively eyelash",
        "imagen": "https://s.alicdn.com/@sc04/kf/He8b6c154741642feb206b07ad29de8c0E.jpg"
      },
      {
        "nombre": "03 Dense eyelash",
        "imagen": "https://s.alicdn.com/@sc04/kf/H8d839d7e4a734857b0b2517daad9df4eh.jpg"
      },
      {
        "nombre": "04 Charm eyelash",
        "imagen": "https://s.alicdn.com/@sc04/kf/Hbb57b111804649e493f85c2d88cb25fcm.jpg"
      },
      {
        "nombre": "05 Cloud eyelash",
        "imagen": "https://s.alicdn.com/@sc04/kf/H54e16aa98065487f9200fe168c8b3d8aY.jpg"
      },
      {
        "nombre": "06 Vitality eyelash",
        "imagen": "https://s.alicdn.com/@sc04/kf/Hb8eef0b9b59044688f50eb3da67461faG.jpg"
      }
    ],
    "tamaños": [
      "Natural",
      "11 mm(0.43in)"
    ],
    "precios": [
      {
        "cantidad": "1 - 200 sets",
        "valor": "$13.99"
      },
      {
        "cantidad": "201 - 1000 sets",
        "valor": "$7.76"
      },
      {
        "cantidad": "\u003e= 1001 sets",
        "valor": "$7.49"
      }
    ],
    "bloque_logistico": "Standard: Shipping fee: FREE shipping | Guaranteed delivery: Nov 25 - Dec 05",
    "detalles": {
      "Curl": "C, D",
      "Delivery time": "7 Days",
      "False Eyelashe Type": "magnetic eyelashes set",
      "Feature": "Reusable, natural soft, Light Weight, Durable",
      "Keywords": "Soft Magnetic Eyelashes",
      "MOQ": "1",
      "Magnet": "10magnets",
      "Name": "Magnet Eyelashes",
      "Number of Items": "1",
      "Product name": "Soft Magnetic Eyelashes",
      "Selling Units": "Single item",
      "Single gross weight": "0.100 kg",
      "Single package size": "8.0X7.0X4.0 cm",
      "brand name": "YANJIE",
      "material": "Fiber",
      "model number": "A29",
      "place of origin": "Fujian, China",
      "size type": "sample size, Travel Size",
      "thickness": "0.05 mm, 0.03 mm",
      "type": "Semi-Hand Made"
    }
  },
  {
    "url": "https://www.alibaba.com/product-detail/Miss-Gooey-12-Colors-cat-Eye_1601539157398.html?spm=a2700.prosearch.normal_offer.d_image.23f067afBH7NrD\u0026selectedCarrierCode=SEMI_MANAGED_PREMIUM%40%40PREMIUM\u0026priceId=fbece069f0f5430aa84b29fd92f587bc",
    "categoria": "makeup",
    "titulo": "Miss Gooey 12 Colors cat Eye Gel Polish Set Hema Free Magnetic cat Eye Gel Polish Nail Art Private Label Uv Gel Nail Polish OEM",
    "imagenes": [
      "https://s.alicdn.com/@sc04/kf/H2697b69fd10c41d69139576fd3fb0f3ds.jpg_960x960q80.jpg",
      "https://s.alicdn.com/@sc04/kf/H00342bc343bc4599b73c7e9b6b5472bab.jpg_960x960q80.jpg",
      "https://s.alicdn.com/@sc04/kf/Hd8353dcf104b46d585f450e507c3b9a39.jpg_960x960q80.jpg",
      "https://s.alicdn.com/@sc04/kf/H0b87b28d32bf4676999c890b838491647.jpg_960x960q80.jpg",
      "https://s.alicdn.com/@sc04/kf/H3a87472643db48ddb4618ef18d16de62o.jpg_960x960q80.jpg",
      "https://s.alicdn.com/@sc04/kf/Ha1f0a5a431f34750917c010bd5c1fea2C.jpg_960x960q80.jpg"
    ],
    "colores": [
      {
        "nombre": "01",
        "imagen": "https://s.alicdn.com/@sc04/kf/H36be9eb7bf9340399c0ce9ff6d615d1f4.jpg"
      },
      {
        "nombre": "02",
        "imagen": "https://s.alicdn.com/@sc04/kf/Hcaa383f5c03c41758046e8f68307a002W.jpg"
      },
      {
        "nombre": "03",
        "imagen": "https://s.alicdn.com/@sc04/kf/H3b6b4be4fb5e4990b4528a00e3796c06a.jpg"
      },
      {
        "nombre": "04",
        "imagen": "https://s.alicdn.com/@sc04/kf/Hada964fa4b24451fbc7dc1ce370cc9c7g.jpg"
      },
      {
        "nombre": "05",
        "imagen": "https://s.alicdn.com/@sc04/kf/H4683285157044ba89238622abfd88a53w.jpg"
      },
      {
        "nombre": "06",
        "imagen": "https://s.alicdn.com/@sc04/kf/H1391a317ba1645b4b9548b4ecb228108s.jpg"
      }
    ],
    "tamaños": [
      "15ml"
    ],
    "precios": [
      {
        "cantidad": "1 - 499 pieces",
        "valor": "$1.35"
      },
      {
        "cantidad": "500 - 2999 pieces",
        "valor": "$1.14"
      },
      {
        "cantidad": "3000 - 9999 pieces",
        "valor": "$0.90"
      },
      {
        "cantidad": "\u003e= 10000 pieces",
        "valor": "$0.80"
      }
    ],
    "bloque_logistico": "Economy: Shipping fee: FREE shipping | Guaranteed delivery: Nov 24 - Dec 03 || Standard: Shipping fee: FREE shipping | Guaranteed delivery: Nov 24 - Dec 02 || Premium: Shipping fee: $13.83 $33.83 for 1 piece | Guaranteed delivery: Nov 20 - Nov 28",
    "detalles": {
      "Application": "Nail Beauty",
      "Color": "Trend Color 300+,Regular Colors 3000+,Contact us for more colors",
      "Feature": "Non-Toxic, Long lasting, hema free, Vegan, Eco-Friendly",
      "Format": "Glitter, Natural, Matte, Metallic",
      "Logo": "Private Label Gel Nail Polish",
      "Material": "Rubber, Magnet, Liquid, Vegan, Natural, Non-Toxic, Jelly",
      "OEM/ODM": "Color, packaging, label, all can be customized",
      "Package": "Complete Nail Polish",
      "Packing": "Box, Bottle",
      "Product name": "12 color cat eye gel",
      "Sample": "Freely Samples Offered",
      "Selling Units": "Single item",
      "Shipping": "DHL\\UPS\\FEDEX\\EMS\\TNT\\SEA\\AIR",
      "Single gross weight": "0.065 kg",
      "Single package size": "8.2X3.2X2.3 cm",
      "Soak off": "Easily Soak Nails Uv Gel",
      "Style": "Luxury, French, Designer, water base",
      "Usage": "Nail Art Products",
      "brand name": "MissGooey",
      "certification": "CE, MSDS",
      "cure": "UV LAMP",
      "lamp source": "UV, LED",
      "material type free": "Non-Toxic",
      "model number": "12 color cat eyes",
      "place of origin": "Guangdong, China",
      "type": "UV Gel"
    }
  },
  {
    "url": "https://www.alibaba.com/product-detail/High-Quality-8pcs-Makeup-Set-Brush_1600478128601.html?spm=a2700.prosearch.normal_offer.d_image.23f067afBH7NrD\u0026selectedCarrierCode=SEMI_MANAGED_STANDARD%40%40STANDARD\u0026priceId=fbece069f0f5430aa84b29fd92f587bc",
    "categoria": "makeup",
    "titulo": "High Quality 8pcs Makeup Set Brush Make up Vegan Synthetic Hair Professional Cosmetic Pink Custom Makeup Brushes With Logo",
    "imagenes": [
      "https://s.alicdn.com/@sc04/kf/H87e9294fbb7d4ee196d826757ee946d5E.jpg_960x960q80.jpg",
      "https://s.alicdn.com/@sc04/kf/Hf90b8780a93842ffb90c79e6a5948fc7Q.jpg_960x960q80.jpg",
      "https://s.alicdn.com/@sc04/kf/H25938374143749bebf087d210c21500fi.jpg_960x960q80.jpg",
      "https://s.alicdn.com/@sc04/kf/H66a6625a6b6e4e338ffa5948c6531cc9V.jpg_960x960q80.jpg",
      "https://s.alicdn.com/@sc04/kf/H6776531c38f54e9ba7c76f3953fc160cQ.jpg_960x960q80.jpg",
      "https://s.alicdn.com/@sc04/kf/He377e7403a264a1bb7317d1f8d817e78L.jpg_960x960q80.jpg"
    ],
    "colores": [
      {
        "nombre": "04",
        "imagen": "https://s.alicdn.com/@sc04/kf/Hb5e33673cd204be89c0dd27688e3fd10j.jpg"
      },
      {
        "nombre": "05",
        "imagen": "https://s.alicdn.com/@sc04/kf/H756de2017c6a489fbeffda5b73a8b8b7t.jpg"
      },
      {
        "nombre": "06",
        "imagen": "https://s.alicdn.com/@sc04/kf/H2ed8b554ac764134871cdb9a4841ec8fc.jpg"
      },
      {
        "nombre": "07",
        "imagen": "https://s.alicdn.com/@sc04/kf/H50aeeb3514154079bd6f01138dbdcd500.jpg"
      },
      {
        "nombre": "08",
        "imagen": "https://s.alicdn.com/@sc04/kf/Hcb2a05e7b1a64dcca9a29e06c22310d2k.jpg"
      },
      {
        "nombre": "09",
        "imagen": "https://s.alicdn.com/@sc04/kf/H39a93ae5dd3a45198e92dd73c0f3676du.jpg"
      }
    ],
    "tamaños": [
      "regular size"
    ],
    "precios": [
      {
        "cantidad": "2 - 99 sets",
        "valor": "$6"
      },
      {
        "cantidad": "100 - 999 sets",
        "valor": "$5.50"
      },
      {
        "cantidad": "\u003e= 1000 sets",
        "valor": "$5.30"
      }
    ],
    "bloque_logistico": "Standard: Shipping fee: $1.20 $21.20 for 2 sets | Guaranteed delivery: Nov 20 - Dec 03, 26.9% delivered ≤ 10 days || Premium: Shipping fee: $6.52 $26.52 for 2 sets | Guaranteed delivery: Nov 22 - Dec 02, 37.8% delivered ≤ 13 days",
    "detalles": {
      "Application": "daily makeup, beauty face makeup, face and eyes",
      "Brand Name": "DIAS",
      "Brush Material": "Synthetic Hair",
      "Feature": "Makes Applying Makeup",
      "Ferrule Material": "Aluminum Ferrule",
      "Handle Material": "Wood",
      "Item Name": "Professional 8pcs Makeup Brush Set",
      "Items Per Set": "8pcs",
      "Logo": "Private Label Acceptable",
      "Logo printing": "Customized Printing Acceptable",
      "MOQ": "2sets",
      "Material": "Synthetic Hair+Wood Handle",
      "Model Number": "DIAS2211",
      "OEM/ODM": "Warmly Welcomed",
      "Place of Origin": "Henan, China",
      "Position": "Ferrule, Thickened Aluminum Tube",
      "Sample time": "1-5 Working Days",
      "Selling Units": "Single item",
      "Shape": "Round, Flat",
      "Single gross weight": "0.300 kg",
      "Single package size": "26X16X11 cm",
      "Style": "Angular Blush, Smudge Brush, Flat Brush",
      "Type": "Face Beauty Makeup Brush",
      "Use": "Face",
      "Used With": "Lip Liner, CONCEALER, BLUSHER, Lip Gloss, Eyebrow Pencil, Eyeliner, FOUNDATION, Eye Shadow, Lip Balm, Lipstick"
    }
  },
  {
    "url": "https://www.alibaba.com/product-detail/Women-s-Sleepwear-Set-Satin-Silk_1600305274469.html?spm=a2700.galleryofferlist.normal_offer.d_image.330513a05Lyrcf\u0026selectedCarrierCode=SEMI_MANAGED_STANDARD%40%40STANDARD\u0026priceId=cb344fc8107c4508ad777b7905c22932",
    "categoria": "Women's sleepwear",
    "titulo": "Women's Sleepwear Set Satin Silk Fabric Designers Pajamas Long Sleeve Plus Size M to 5XL",
    "imagenes": [
      "https://s.alicdn.com/@sc04/kf/H52b1d38e28d144ff8e8a9558551652098.jpg_960x960q80.jpg",
      "https://s.alicdn.com/@sc04/kf/H06ba275a538b466b9fc7acba31f903355.jpg_960x960q80.jpg",
      "https://s.alicdn.com/@sc04/kf/H11e88bfd6e194c4da03b1a158256e7a24.jpg_960x960q80.jpg",
      "https://s.alicdn.com/@sc04/kf/H9ca52108bb9243739d69345500f6ba39e.jpg_960x960q80.jpg",
      "https://s.alicdn.com/@sc04/kf/H2b17808b9c434c088dff9dcc79d3f48dc.jpg_960x960q80.jpg",
      "https://s.alicdn.com/@sc04/kf/H5739378b073e47e78212d740e1a35ea4g.jpg_960x960q80.jpg"
    ],
    "colores": [
      {
        "nombre": "21BL-black",
        "imagen": "https://s.alicdn.com/@sc04/kf/He3874617ed76433b85e501af0f9215d95.jpg"
      },
      {
        "nombre": "21BL-red",
        "imagen": "https://s.alicdn.com/@sc04/kf/H92ad9e57726343e7999e75a90c46a93eu.jpg"
      },
      {
        "nombre": "21BL-blue mist",
        "imagen": "https://s.alicdn.com/@sc04/kf/Hc2c1b6dec7964206b382a6f1bd6356458.jpg"
      },
      {
        "nombre": "21BL-champagne",
        "imagen": "https://s.alicdn.com/@sc04/kf/H87211babfb234504abaf87a5b7e7dae98.jpg"
      },
      {
        "nombre": "21BL-pink",
        "imagen": "https://s.alicdn.com/@sc04/kf/H4d4e95f2c914451cb20c4b7d0d27df335.jpg"
      },
      {
        "nombre": "21BL-blue",
        "imagen": "https://s.alicdn.com/@sc04/kf/H6944f5507fd54c8f82446f8bc749629aa.jpg"
      }
    ],
    "tamaños": [
      "5 XL",
      "4 XL",
      "3 XL",
      "2 XL",
      "XL",
      "L",
      "M"
    ],
    "precios": [
      {
        "cantidad": "Minimum order quantity: 2 pieces",
        "valor": "$2-4.60"
      }
    ],
    "bloque_logistico": "Premium: Shipping fee: FREE shipping | Guaranteed delivery: Nov 23 - Dec 05, 36.0% delivered ≤ 14 days || Standard: Shipping fee: FREE shipping | Guaranteed delivery: Nov 24 - Dec 09, 39.1% delivered ≤ 11 days",
    "detalles": {
      "7 days sample order lead time": "Support",
      "Age Group": "Adults",
      "Brand Name": "No",
      "Closure Type": "Elastic Waist",
      "Collar": "Turn-down Collar",
      "Fabric Type": "Satin",
      "Feature": "Thermal, Breathable, Quick Dry, Plus Size",
      "Item Type": "Pajamas",
      "Length": "Full Length",
      "Material": "Polyester / Cotton",
      "Model Number": "21BL",
      "Number of Pieces": "2",
      "Pattern Type": "Solid",
      "Place of Origin": "Guangdong, China",
      "Printing Methods": "Other",
      "Product Care Instructions": "Handwash",
      "Season": "Winter",
      "Selling Units": "Single item",
      "Single gross weight": "0.350 kg",
      "Single package size": "35X30X1 cm",
      "Sleeve Length(cm)": "Full",
      "Supply Type": "In-Stock Items",
      "Technics": "GARMENT DYED, Plain Dyed, Embroidered, Printed"
    }
  },
  {
    "url": "https://www.alibaba.com/product-detail/Wholesale-Simple-Soft-Black-Family-Pajamas_1600927443192.html?spm=a2700.galleryofferlist.normal_offer.d_image.330513a05Lyrcf\u0026selectedCarrierCode=SEMI_MANAGED_STANDARD%40%40STANDARD\u0026priceId=cb344fc8107c4508ad777b7905c22932",
    "categoria": "  ",
    "titulo": "Wholesale Simple Soft Black Family Pajamas Long Sleeves Elastic Waist Knitted Fabric Women's Pajama Set for Spring Fall Time",
    "imagenes": [
      "https://s.alicdn.com/@sc04/kf/H9129c728d93a457ab5c701499eb7a033R.jpg_960x960q80.jpg",
      "https://s.alicdn.com/@sc04/kf/H8042ccab07ac4bb2b907567f71859345q.jpg_960x960q80.jpg",
      "https://s.alicdn.com/@sc04/kf/H182eeb0f309d4c6287c8dcfb386dd97eU.jpg_960x960q80.jpg",
      "https://s.alicdn.com/@sc04/kf/Hf4f793cb942a420c94b4d35f269ef41dd.jpg_960x960q80.jpg",
      "https://s.alicdn.com/@sc04/kf/H4fff79e5423d4487a0ccb355f2cf9b05F.jpg_960x960q80.jpg",
      "https://s.alicdn.com/@sc04/kf/H98e92f3d0c554165a2f1e7cfcb5f6f23F.jpg_960x960q80.jpg"
    ],
    "colores": [
      {
        "nombre": "Black",
        "imagen": "https://s.alicdn.com/@sc04/kf/He9ddeabb48764577a41e6ca2699899f5K.jpg"
      }
    ],
    "tamaños": [
      "M/1",
      "L/2",
      "XL/3",
      "XXL/4",
      "3XL/5",
      "4XL/6",
      "5XL/7"
    ],
    "precios": [
      {
        "cantidad": "Minimum order quantity: 2 pieces",
        "valor": "$3.99-4.72"
      }
    ],
    "bloque_logistico": "Standard: Shipping fee: FREE shipping | Guaranteed delivery: Nov 24 - Dec 09, 30.1% delivered ≤ 11 days || Economy: Shipping fee: FREE shipping | Guaranteed delivery: Dec 13 - Jan 23, 33.9% delivered ≤ 34 days || Premium: Shipping fee: $0.35 $20.35 for 2 pieces | Guaranteed delivery: Nov 23 - Dec 05, 36.0% delivered ≤ 14 days",
    "detalles": {
      "7 days sample order lead time": "Not Support",
      "Age Group": "Adults Teen Girls Women Ladies",
      "Closure Type": "Elastic Waist",
      "Fabric Type": "Knitted",
      "Feature": "Soft",
      "Gender": "Women",
      "Item Type": "Nightgowns",
      "Keywords": "Pajamas for women",
      "Length": "Full Length",
      "MOQ": "1 Piece",
      "Material": "100% Polyester",
      "Neckline": "Turn-down Collar",
      "Number of Pieces": "2",
      "Occasion": "Homewear Sleepwear",
      "Packing": "Opp Bag",
      "Pattern": "Other",
      "Place of Origin": "Guangdong, China",
      "Print Method": "Other",
      "Product Name": "Pajamas for women",
      "Product Type": "Ladies Sleepwear Nighties",
      "Season": "Spring, Autumn",
      "Selling Units": "Single item",
      "Single gross weight": "0.461 kg",
      "Single package size": "34X26X0.5 cm",
      "Sleeve": "Long sleeve",
      "Sleeve Length": "Full",
      "Style": "Comfortable simple style",
      "Supply Type": "Oem Service",
      "Technic": "Plain Dyed",
      "Weaving method": "Knitted"
    }
  },
  {
    "url": "https://www.alibaba.com/product-detail/Pajamas-Women-s-Summer-Milk-Silk_1600305647612.html?spm=a2700.galleryofferlist.normal_offer.d_image.330513a05Lyrcf\u0026selectedCarrierCode=SEMI_MANAGED_STANDARD%40%40STANDARD\u0026priceId=cb344fc8107c4508ad777b7905c22932",
    "categoria": "Women's sleepwear",
    "titulo": "Pajamas Women's Summer Milk Silk Short Sleeve Shorts Trousers 3 Piece Set Korean Style Cartoon Housewear Women's Sleepwear",
    "imagenes": [
      "https://s.alicdn.com/@sc04/kf/H15e60521ac9849e8b5e0f4c2bf2d93b4i.jpg_960x960q80.jpg",
      "https://s.alicdn.com/@sc04/kf/He768e038f2d44d6f92178e6a139be5775.jpg_960x960q80.jpg",
      "https://s.alicdn.com/@sc04/kf/H5456a165411240aca2e34365884bb6dcr.jpg_960x960q80.jpg",
      "https://s.alicdn.com/@sc04/kf/H105bea49578c415fbf5073205fd108746.jpg_960x960q80.jpg",
      "https://s.alicdn.com/@sc04/kf/Hfe74302b21494fd5bbb0717fbcd826f20.jpg_960x960q80.jpg",
      "https://s.alicdn.com/@sc04/kf/H83579af703e64cbc89bd918656fafab98.jpg_960x960q80.jpg"
    ],
    "colores": [
      {
        "nombre": "1",
        "imagen": "https://s.alicdn.com/@sc04/kf/Hbd9d96673b664158b43c6514d580e244J.jpg"
      },
      {
        "nombre": "2",
        "imagen": "https://s.alicdn.com/@sc04/kf/Hc1a72ca81d494d6a829609c8926023dfK.jpg"
      },
      {
        "nombre": "3",
        "imagen": "https://s.alicdn.com/@sc04/kf/Hd2443d0e1bb741a1a0a2ff7b68848be5K.jpg"
      },
      {
        "nombre": "4",
        "imagen": "https://s.alicdn.com/@sc04/kf/H907ec8b871fe42598b4da5afa86d5bc2Q.jpg"
      },
      {
        "nombre": "5",
        "imagen": "https://s.alicdn.com/@sc04/kf/Hc09d60f9ddb64f0eb8062890e214c363u.jpg"
      },
      {
        "nombre": "6",
        "imagen": "https://s.alicdn.com/@sc04/kf/Haf5c353df40743ffa808b7475b7bbd012.jpg"
      }
    ],
    "tamaños": [
      "One size"
    ],
    "precios": [
      {
        "cantidad": "2 - 49 sets",
        "valor": "$3.80"
      },
      {
        "cantidad": "50 - 99 sets",
        "valor": "$3.50"
      },
      {
        "cantidad": "100 - 499 sets",
        "valor": "$3.30"
      },
      {
        "cantidad": "\u003e= 500 sets",
        "valor": "$2.98"
      }
    ],
    "bloque_logistico": "Premium: Shipping fee: FREE shipping | Guaranteed delivery: Nov 23 - Dec 05, 39.8% delivered ≤ 15 days || Standard: Shipping fee: FREE shipping | Guaranteed delivery: Nov 24 - Dec 09, 31.4% delivered ≤ 11 days",
    "detalles": {
      "7 days sample order lead time": "Support",
      "Brand Name": "huiou",
      "Closure Type": "Elastic Waist",
      "Color": "Picture Shows",
      "Fabric Type": "Knitted",
      "Feature": "Quick Dry, Breathable",
      "Gender": "Women Ladies",
      "Item Type": "Nightgowns",
      "Keywords": "Sexy Women Pajamas",
      "Length": "Full Length",
      "MOQ": "2sets",
      "Material": "100% Polyester",
      "Neckline": "Round Neck",
      "Number of Pieces": "3",
      "OEM": "Accept Customize Size",
      "Packaging": "1 Piece Packaging",
      "Pattern": "Cartoon",
      "Place of Origin": "Guangdong, China",
      "Print Method": "Digital Printing",
      "Product Name": "Milk Silk Mickey Pajamas Sets",
      "Season": "Spring Winter Autumn Summer",
      "Selling Units": "Single item",
      "Service": "OEM ODM Acceptable",
      "Shipping  Way": "EMS DHL FedexIE UPS TNT",
      "Single gross weight": "0.450 kg",
      "Single package size": "1X1X1 cm",
      "Sleeve Length": "Short",
      "Supply Type": "In-Stock Items",
      "Technic": "Plain Dyed",
      "Weaving method": "Knitted"
    }
  },
  {
    "url": "https://www.alibaba.com/product-detail/Wholesale-Women-s-Real-Mulberry-Silk_1601032684049.html?spm=a2700.galleryofferlist.normal_offer.d_image.330513a05Lyrcf\u0026selectedCarrierCode=SEMI_MANAGED_STANDARD%40%40STANDARD\u0026priceId=cb344fc8107c4508ad777b7905c22932",
    "categoria": "Women's sleepwear",
    "titulo": "Wholesale Women's Real Mulberry Silk Nightgown Set V-Neck Satin PJs Top and Pants Summer XL Size Solid Color Sleepwear",
    "imagenes": [
      "https://s.alicdn.com/@sc04/kf/Hf09d36ad48404f77bec3a63e0275f08eH.jpg_960x960q80.jpg",
      "https://s.alicdn.com/@sc04/kf/H30b4ee2dfbea435eb969f0bdad0f14eeC.jpg_960x960q80.jpg",
      "https://s.alicdn.com/@sc04/kf/H12ccdddeb4954089bc07a91fe86468e9k.jpg_960x960q80.jpg",
      "https://s.alicdn.com/@sc04/kf/H24f0fbff473f4727bb0883f00409da00k.jpg_960x960q80.jpg",
      "https://s.alicdn.com/@sc04/kf/H0d670e5bf4d14a62acc5bb4eb5f7c3c1T.jpg_960x960q80.jpg",
      "https://s.alicdn.com/@sc04/kf/H53ae33f5b2cd4a429fd7fddf2759107cN.jpg_960x960q80.jpg"
    ],
    "colores": [
      {
        "nombre": "Blue",
        "imagen": "https://s.alicdn.com/@sc04/kf/H8a2c47e2bb6a4c2d820830041c0961d7l.jpg"
      },
      {
        "nombre": "Black",
        "imagen": "https://s.alicdn.com/@sc04/kf/H1b17e03435bc4b6a91e306098c118849T.jpg"
      },
      {
        "nombre": "Red",
        "imagen": "https://s.alicdn.com/@sc04/kf/H313693d5d1524e46ae851c09c319d8car.jpg"
      },
      {
        "nombre": "Pink",
        "imagen": "https://s.alicdn.com/@sc04/kf/Hd7c68bba3957468d815760f426ed3febz.jpg"
      },
      {
        "nombre": "Green",
        "imagen": "https://s.alicdn.com/@sc04/kf/H19634379a1cb4cbbbebab383bc2dfcd3N.jpg"
      },
      {
        "nombre": "Sky Blue",
        "imagen": "https://s.alicdn.com/@sc04/kf/Hc9797f653c6440c59481ce3f1dd646a93.jpg"
      }
    ],
    "tamaños": [
      "M",
      "L",
      "XL",
      "2 XL"
    ],
    "precios": [
      {
        "cantidad": "2 - 49 pieces",
        "valor": "$59.90"
      },
      {
        "cantidad": "50 - 499 pieces",
        "valor": "$55.90"
      },
      {
        "cantidad": "\u003e= 500 pieces",
        "valor": "$54.90"
      }
    ],
    "bloque_logistico": "Premium: Shipping fee: FREE shipping | Guaranteed delivery: Nov 23 - Dec 05, 39.8% delivered ≤ 15 days || Standard: Shipping fee: FREE shipping | Guaranteed delivery: Nov 24 - Dec 09, 31.4% delivered ≤ 11 days",
    "detalles": {
      "7 days sample order lead time": "Support",
      "Advantage": "Eco-friendly Soft Comfortable",
      "Brand Name": "ESASILK",
      "Closure Type": "Drawstring",
      "Decoration": "ONLY",
      "Fabric": "Silk stain",
      "Fabric Type": "Satin",
      "Fabric Weight": "16MM",
      "Feature": "Quick Dry, Breathable, Smooth, Soft",
      "Gender": "Girl Lady Women",
      "Item Type": "Pajamas",
      "Keywords": "Pure Silk dress Mini Sleepwear",
      "Length": "Full Length",
      "Logo": "Customized Logo",
      "MOQ": "2PCS",
      "Material": "100% Silk",
      "Model Number": "D-21950380",
      "Neckline": "V-neck",
      "Number of Pieces": "1",
      "Pattern": "Solid",
      "Place of Origin": "Jiangsu, China",
      "Print Method": "None",
      "Product Care Instructions": "Handwash",
      "Product Name": "V Neck real silk Pjs Nightgowns Top And Pants Sets For Women",
      "Product Type": "Sexy Sleepwear Dress",
      "Season": "Winter, Summer, Spring, Autumn",
      "Selling Units": "Single item", 
      "Single gross weight": "0.287 kg",
      "Single package size": "40X25X2 cm",
      "Sleeve Length": "Full",
      "Style": "Casual",
      "Supply Type": "Oem Service",
      "Technic": "None",
      "Wash": "Hand Wash",
      "Weaving method": "Knitted"
    }
  }
]